setup.py
ulawwave/__init__.py
ulawwave.egg-info/PKG-INFO
ulawwave.egg-info/SOURCES.txt
ulawwave.egg-info/dependency_links.txt
ulawwave.egg-info/top_level.txt