Metadata-Version: 1.1
Name: ulawwave
Version: 0.1.2
Summary: extension to the standard wave module to deal with g711 (ulaw) and alaw
Home-page: https://github.com/haraldsinger/ulawwave
Author: Eric Woudenberg, Harald Singer
Author-email: haraldgsinger@gmail.com
License: UNKNOWN
Download-URL: https://github.com/haraldsinger/ulawwave
Keywords: audio,ulaw,alaw,g711,ivr
Platform: UNKNOWN
